glaider/__init__.py
glaider/authenticator.py
glaider/init.py
glaider/data_processor/__init__.py
glaider/data_processor/data_processor.py
glaider/entities/__init__.py
glaider/entities/ip_checker.py
glaider/entities/logger.py
glaider/entities/models.py
glaider/entities/pii_scrubber.py
glaider/entities/utils.py
glaider/interfaces/__init__.py
glaider/interfaces/cohere.py
glaider/interfaces/openai.py
glaider/protection/__init__.py
glaider/protection/protection.py
glaider/providers/__init__.py
glaider/providers/cohere_wrapper.py
glaider/providers/openai_wrapper.py
glaider-0.2.1.dist-info/LICENSE
glaider-0.2.1.dist-info/METADATA
glaider-0.2.1.dist-info/WHEEL
glaider-0.2.1.dist-info/top_level.txt
glaider-0.2.1.dist-info/RECORD
