Metadata-Version: 2.1
Name: glaider
Version: 0.2.1
Summary: A Python library to secure gen AI
Home-page: 
Author: Lorenzo Abati
Author-email: lorenzo@glaider.it
Classifier: Development Status :: 3 - Alpha
Classifier: Intended Audience :: Developers
Classifier: License :: OSI Approved :: MIT License
Classifier: Programming Language :: Python :: 3.9
License-File: LICENSE
Requires-Dist: cohere ==4.11.2
Requires-Dist: openai ==0.27.8
Requires-Dist: pydantic ==1.10.9
Requires-Dist: requests ==2.31.0
